{
  "persons": [
    {
      "name": "Mary Poppendieck",
      "number": "39-23-6423122",
      "id": 505
    },
    {
      "name": "Mary Poppendieck",
      "number": "39-23-6423122",
      "id": 598
    },
    {
      "name": "Mary Poppendieck",
      "number": "39-23-6423122",
      "id": 5
    },
    {
      "name": "Mary Poppendieck",
      "number": "39-23-6423122",
      "id": 5567
    },
    {
      "name": "Mary Poppendieck",
      "number": "39-23-6423122",
      "id": 123
    },
    {
      "name": "testing",
      "number": "12344",
      "id": 11
    }
  ]
}